[
    {
        "job_role": "Lead Jobs Developer",
        "subject": "Excited to apply for Lead Jobs Developer at your organization",
        "email": "Dear Ethan,\n\nI came across your profile on LinkedIn and was impressed by your experience in software development. With over 2 years of experience in leading jobs development, I believe you would be a great fit for our team at AtliQ.\n\nWe're currently looking for a skilled software developer to help us create a new feature for our remote job platform. As a Lead Jobs Developer, you will be responsible for designing and implementing a new mode for our platform that allows users to view lead jobs. If you have experience with software development and are interested in working on a challenging project, we want to hear from you!\n\nI'd love to see some examples of your work. You can find my portfolio links below for reference:\n\n- https://example.com/ml-python-portfolio (check out my machine learning projects with Python)\n- https://example.com/ml-python-portfolio (another example of my Python skills)\n- https://example.com/devops-portfolio (take a look at my DevOps experience)\n- https://example.com/devops-portfolio (more examples of my DevOps work)\n- https://example.com/xamarin-portfolio (check out my Xamarin projects)\n- https://example.com/xamarin-portfolio (another example of my Xamarin skills)\n\nIf you're interested in learning more about this opportunity, I'd be happy to set up a call to discuss further. Please let me know if you're available to talk this week.\n\nBest regards,\nMohan",
        "tone": "Professional",
        "timestamp": "2025-11-12 18:21:41"
    },
    {
        "job_role": "Lead Jobs Developer",
        "subject": "Excited to apply for Lead Jobs Developer at your organization",
        "email": "Dear Ethan,\n\nI came across your profile on LinkedIn and was impressed by your experience in software development. With over 2 years of experience in leading jobs development, I believe you would be a great fit for our team at AtliQ.\n\nWe're currently looking for a skilled software developer to help us create a new feature for our remote job platform. As a Lead Jobs Developer, you will be responsible for designing and implementing a new mode for our platform that allows users to view lead jobs. If you have experience with software development and are interested in working on a challenging project, we want to hear from you!\n\nI'd love to see some examples of your work. You can find my portfolio links below for reference:\n\n- https://example.com/ml-python-portfolio (check out my machine learning projects with Python)\n- https://example.com/ml-python-portfolio (another example of my Python skills)\n- https://example.com/devops-portfolio (take a look at my DevOps experience)\n- https://example.com/devops-portfolio (more examples of my DevOps work)\n- https://example.com/xamarin-portfolio (check out my Xamarin projects)\n- https://example.com/xamarin-portfolio (another example of my Xamarin skills)\n\nIf you're interested in learning more about this opportunity, I'd be happy to set up a call to discuss further. Please let me know if you're available to talk this week.\n\nBest regards,\nMohan",
        "tone": "Professional",
        "timestamp": "2025-11-12 18:22:20"
    }
]